vakantie/__init__.py
vakantie/calendar_extractor.py
vakantie/calendar_info.py
vakantie-0.1.dist-info/LICENSE.txt
vakantie-0.1.dist-info/METADATA
vakantie-0.1.dist-info/WHEEL
vakantie-0.1.dist-info/top_level.txt
vakantie-0.1.dist-info/RECORD
