Metadata-Version: 2.1
Name: vakantie
Version: 0.1
Summary: A Package to get all holidays starting from 2015
Home-page: https://github.com/rupaai/vakantie
Author: Labiba Kanij Rupty
Author-email: labibakanij@gmail.com
License: UNKNOWN
Platform: UNKNOWN
Classifier: Programming Language :: Python :: 3
Classifier: License :: OSI Approved :: MIT License
Classifier: Operating System :: OS Independent
License-File: LICENSE.txt
Requires-Dist: pandas
Requires-Dist: beautifulsoup4
Requires-Dist: requests
Requires-Dist: lxml
